htklite/__init__.py
htklite/utils.py
htklite/preprocessing/__init__.py
htklite/preprocessing/_linalg.py
htklite/preprocessing/color_convolution.py
htklite/preprocessing/color_deconvolution.py
htklite/preprocessing/color_conversion/__init__.py
htklite/preprocessing/color_conversion/lab_mean_std.py
htklite/preprocessing/color_conversion/lab_to_rgb.py
htklite/preprocessing/color_conversion/od_to_rgb.py
htklite/preprocessing/color_conversion/rgb_to_hsi.py
htklite/preprocessing/color_conversion/rgb_to_lab.py
htklite/preprocessing/color_conversion/rgb_to_od.py
htklite/preprocessing/color_conversion/rgb_to_sda.py
htklite/preprocessing/color_conversion/sda_to_rgb.py
htklite-0.0.1.dist-info/LICENSE
htklite-0.0.1.dist-info/METADATA
htklite-0.0.1.dist-info/WHEEL
htklite-0.0.1.dist-info/top_level.txt
htklite-0.0.1.dist-info/RECORD
